an_envmanager/__init__.py
an_envmanager/envmanager.py
an_envmanager-1.3.2.dist-info/licenses/LICENSE
an_envmanager-1.3.2.dist-info/METADATA
an_envmanager-1.3.2.dist-info/WHEEL
an_envmanager-1.3.2.dist-info/top_level.txt
an_envmanager-1.3.2.dist-info/RECORD
