Metadata-Version: 2.4
Name: an_envmanager
Version: 1.3.2
Summary: A package for an_envmanager.
Home-page: https://github.com/Atsushi888/Atsushi888
Author: Atsushi888
Author-email: Atsushi888 <vtgrotxu@gmail.com>
Project-URL: Homepage, https://github.com/Atsushi888/an_envmanager
Project-URL: Repository, https://github.com/Atsushi888/an_envmanager
Requires-Python: >=3.6
License-File: LICENSE
Dynamic: author
Dynamic: home-page
Dynamic: license-file
Dynamic: requires-python
